spring_ready/__init__.py
spring_ready/core.py
spring_ready/exceptions.py
spring_ready/retry.py
spring_ready/actuator/__init__.py
spring_ready/actuator/auditevents.py
spring_ready/actuator/beans.py
spring_ready/actuator/caches.py
spring_ready/actuator/configprops.py
spring_ready/actuator/discovery.py
spring_ready/actuator/env.py
spring_ready/actuator/health.py
spring_ready/actuator/heapdump.py
spring_ready/actuator/httptrace.py
spring_ready/actuator/info.py
spring_ready/actuator/logfile.py
spring_ready/actuator/loggers.py
spring_ready/actuator/mappings.py
spring_ready/actuator/metrics.py
spring_ready/actuator/prometheus.py
spring_ready/actuator/refresh.py
spring_ready/actuator/scheduledtasks.py
spring_ready/actuator/threaddump.py
spring_ready/config/__init__.py
spring_ready/config/loader.py
spring_ready/eureka/__init__.py
spring_ready/eureka/client.py
spring_ready/eureka/discovery.py
spring_ready/eureka/instance.py
spring_ready/eureka/registry.py
spring_ready/integrations/__init__.py
spring_ready/integrations/fastapi.py
spring_ready_python-0.1.0.dist-info/METADATA
spring_ready_python-0.1.0.dist-info/WHEEL
spring_ready_python-0.1.0.dist-info/RECORD
