Metadata-Version: 2.4
Name: spring-ready-python
Version: 0.1.0
Summary: Make Python FastAPI apps work with Spring Boot ecosystem (Eureka, Config Server, Actuator)
Project-URL: Homepage, https://github.com/tcivie/spring-ready-python
Project-URL: Issues, https://github.com/tcivie/spring-ready-python/issues
Author-email: Gleb Tcivie <gleb@tcivie.com>
License-Expression: MIT
Keywords: actuator,config-server,eureka,fastapi,microservices,prometheus,spring-boot
Classifier: Development Status :: 4 - Beta
Classifier: Framework :: FastAPI
Classifier: Intended Audience :: Developers
Classifier: License :: OSI Approved :: MIT License
Classifier: Operating System :: OS Independent
Classifier: Programming Language :: Python :: 3
Classifier: Programming Language :: Python :: 3.9
Classifier: Programming Language :: Python :: 3.10
Classifier: Programming Language :: Python :: 3.11
Classifier: Programming Language :: Python :: 3.12
Classifier: Topic :: Software Development :: Libraries :: Application Frameworks
Requires-Python: >=3.9
Requires-Dist: fastapi>=0.100.0
Requires-Dist: requests>=2.31.0
Provides-Extra: all
Requires-Dist: prometheus-client>=0.19.0; extra == 'all'
Requires-Dist: spring-config-client-python>=0.1.0; extra == 'all'
Provides-Extra: config
Requires-Dist: spring-config-client-python>=0.1.0; extra == 'config'
Provides-Extra: dev
Requires-Dist: httpx>=0.24.0; extra == 'dev'
Requires-Dist: pytest-asyncio>=0.21.0; extra == 'dev'
Requires-Dist: pytest-cov>=4.1.0; extra == 'dev'
Requires-Dist: pytest>=7.4.0; extra == 'dev'
Requires-Dist: uvicorn>=0.23.0; extra == 'dev'
Provides-Extra: metrics
Requires-Dist: prometheus-client>=0.19.0; extra == 'metrics'
